configclass.py
configclass-0.2.0.dist-info/LICENSE
configclass-0.2.0.dist-info/METADATA
configclass-0.2.0.dist-info/WHEEL
configclass-0.2.0.dist-info/top_level.txt
configclass-0.2.0.dist-info/RECORD
