Metadata-Version: 2.1
Name: configclass
Version: 0.2.0
Summary: A Python to class to hold configuration values.
Home-page: https://github.com/schettino72/configclass/
Author: Eduardo Naufel Schettino
Author-email: schettino72@gmail.com
License: MIT
Keywords: dict,config
Platform: any
Classifier: Development Status :: 4 - Beta
Classifier: Intended Audience :: Developers
Classifier: License :: OSI Approved :: MIT License
Classifier: Natural Language :: English
Classifier: Operating System :: OS Independent
Classifier: Programming Language :: Python
Classifier: Programming Language :: Python :: 3
Classifier: Programming Language :: Python :: 3.6
Classifier: Programming Language :: Python :: 3.7
Classifier: Programming Language :: Python :: 3.8
Classifier: Programming Language :: Python :: 3 :: Only
Classifier: Topic :: Software Development :: Libraries
Classifier: Topic :: Software Development :: Libraries :: Python Modules
Requires-Dist: mergedict (>=0.2.0)
